{"i2w": {"0": "<NULL>", "1": "<s>", "2": "</s>", "3": "this", "4": "the", "5": "a", "6": "and", "7": "if", "8": "is", "9": "overridden", "10": "to", "11": "performance", "12": "that", "13": "not", "14": "replacement", "15": "safe", "16": "range", "17": "an", "18": "for", "19": "new", "20": "link", "21": "reader", "22": "source", "23": "returns", "24": "length", "25": "improve", "26": "rough", "27": "benchmarking", "28": "shows", "29": "almost", "30": "doubles", "31": "speed", "32": "when", "33": "processing", "34": "strings", "35": "do", "36": "require", "37": "any", "38": "escaping", "39": "escapes", "40": "single", "41": "unicode", "42": "code", "43": "point", "44": "using", "45": "array", "46": "values", "47": "given", "48": "character", "49": "does", "50": "have", "51": "explicit", "52": "lies", "53": "outside", "54": "then", "55": "opens", "56": "buffered", "57": "reading", "58": "from", "59": "method", "60": "independent", "61": "each", "62": "time", "63": "it", "64": "called", "65": "of", "66": "in", "67": "chars", "68": "even", "69": "doing", "70": "so", "71": "requires", "72": "opening", "73": "traversing", "74": "entire", "75": "stream", "76": "avoid", "77": "potentially", "78": "expensive", "79": "operation", "80": "see", "81": "known", "82": "<UNK>"}, "w2i": {"<NULL>": 0, "<s>": 1, "</s>": 2, "this": 3, "the": 4, "a": 5, "and": 6, "if": 7, "is": 8, "overridden": 9, "to": 10, "performance": 11, "that": 12, "not": 13, "replacement": 14, "safe": 15, "range": 16, "an": 17, "for": 18, "new": 19, "link": 20, "reader": 21, "source": 22, "returns": 23, "length": 24, "improve": 25, "rough": 26, "benchmarking": 27, "shows": 28, "almost": 29, "doubles": 30, "speed": 31, "when": 32, "processing": 33, "strings": 34, "do": 35, "require": 36, "any": 37, "escaping": 38, "escapes": 39, "single": 40, "unicode": 41, "code": 42, "point": 43, "using": 44, "array": 45, "values": 46, "given": 47, "character": 48, "does": 49, "have": 50, "explicit": 51, "lies": 52, "outside": 53, "then": 54, "opens": 55, "buffered": 56, "reading": 57, "from": 58, "method": 59, "independent": 60, "each": 61, "time": 62, "it": 63, "called": 64, "of": 65, "in": 66, "chars": 67, "even": 68, "doing": 69, "so": 70, "requires": 71, "opening": 72, "traversing": 73, "entire": 74, "stream": 75, "avoid": 76, "potentially": 77, "expensive": 78, "operation": 79, "see": 80, "known": 81, "<UNK>": 82}, "word_count": {"this": 5, "the": 5, "a": 4, "and": 3, "if": 3, "is": 2, "overridden": 2, "to": 2, "performance": 2, "that": 2, "not": 2, "replacement": 2, "safe": 2, "range": 2, "an": 2, "for": 2, "new": 2, "link": 2, "reader": 2, "source": 2, "returns": 2, "length": 2, "improve": 1, "rough": 1, "benchmarking": 1, "shows": 1, "almost": 1, "doubles": 1, "speed": 1, "when": 1, "processing": 1, "strings": 1, "do": 1, "require": 1, "any": 1, "escaping": 1, "escapes": 1, "single": 1, "unicode": 1, "code": 1, "point": 1, "using": 1, "array": 1, "values": 1, "given": 1, "character": 1, "does": 1, "have": 1, "explicit": 1, "lies": 1, "outside": 1, "then": 1, "opens": 1, "buffered": 1, "reading": 1, "from": 1, "method": 1, "independent": 1, "each": 1, "time": 1, "it": 1, "called": 1, "of": 1, "in": 1, "chars": 1, "even": 1, "doing": 1, "so": 1, "requires": 1, "opening": 1, "traversing": 1, "entire": 1, "stream": 1, "avoid": 1, "potentially": 1, "expensive": 1, "operation": 1, "see": 1, "known": 1}}